Wixy/Api.py
Wixy/__init__.py
wixy-1.0.0.dist-info/licenses/LICENSE
wixy-1.0.0.dist-info/METADATA
wixy-1.0.0.dist-info/WHEEL
wixy-1.0.0.dist-info/top_level.txt
wixy-1.0.0.dist-info/RECORD
