Metadata-Version: 2.4
Name: Wixy
Version: 1.0.0
Summary: A complete library for interacting with nestcode.org
Home-page: https://github.com/N3x74/WixyPy
Author: H O S S E I N
Author-email: 4.ho3ein@gmail.com
License: MIT
Classifier: Programming Language :: Python :: 3
Classifier: Programming Language :: Python :: 3.9
Classifier: License :: OSI Approved :: MIT License
Classifier: Operating System :: OS Independent
Requires-Python: >=3.7
License-File: LICENSE
Requires-Dist: httpx>=0.27.0
Dynamic: license-file
